interactive_select/__init__.py
interactive_select/cli.py
interactive_select/core.py
interactive_select/exceptions.py
interactive_select-0.4.0.dist-info/entry_points.txt
interactive_select-0.4.0.dist-info/WHEEL
interactive_select-0.4.0.dist-info/METADATA
interactive_select-0.4.0.dist-info/RECORD
