Metadata-Version: 2.1
Name: interactive-select
Version: 0.4.0
Summary: 
Author: 0djentd
Requires-Python: >=3.10,<4.0
Classifier: Programming Language :: Python :: 3
Classifier: Programming Language :: Python :: 3.10
